cnquant/__init__.py
cnquant/update_data.py
cnquant/api/__init__.py
cnquant/config/__init__.py
cnquant/config/config.py
cnquant/config/config_columns.py
cnquant/config/config_data_path.py
cnquant/config/config_index.py
cnquant/config/data_columns/README.md
cnquant/config/data_columns/dividend_ths_cn_columns.py
cnquant/core/__init__.py
cnquant/core/api.py
cnquant/core/concat_dfs.py
cnquant/core/format_filename.py
cnquant/core/format_symbol.py
cnquant/core/get_web_data.py
cnquant/core/get_web_data_em.py
cnquant/core/list2txt.py
cnquant/core/name_symbol.py
cnquant/core/parse_address.py
cnquant/core/run_multi_func.py
cnquant/core/txt2list.py
cnquant/data/README.md
cnquant/data/__init__.py
cnquant/data/actual_controller.py
cnquant/data/api.py
cnquant/data/blacklist.py
cnquant/data/history_name.py
cnquant/data/market_data.py
cnquant/data/trading_day.py
cnquant/data/business/__init__.py
cnquant/data/business/business_scope.py
cnquant/data/business/main_business_analysis_ths.py
cnquant/data/business/main_business_composition_analysis.py
cnquant/data/business/main_business_ths.py
cnquant/data/company/__init__.py
cnquant/data/company/company_information.py
cnquant/data/company/company_location.py
cnquant/data/company/ipo_information.py
cnquant/data/company/sw_industry_classification_ths.py
cnquant/data/dividend/__init__.py
cnquant/data/dividend/detailed_dividend_em.py
cnquant/data/dividend/dividend_em.py
cnquant/data/dividend/dividend_ths.py
cnquant/data/finance/__init__.py
cnquant/data/finance/balance_sheet.py
cnquant/data/finance/cash_flow.py
cnquant/data/finance/income_statement.py
cnquant/data/finance/main_index.py
cnquant/data/holder/__init__.py
cnquant/data/holder/holder.py
cnquant/data/holder/holder_num.py
cnquant/data/klines/__init__.py
cnquant/data/klines/index_klines_em.py
cnquant/data/klines/stock_klines_em.py
cnquant/data/klines/two_market_amount.py
cnquant/data/symbol/__init__.py
cnquant/data/symbol/get_bz_symbols.py
cnquant/data/symbol/get_sh_symbols.py
cnquant-1.1.0.dist-info/METADATA
cnquant-1.1.0.dist-info/WHEEL
cnquant-1.1.0.dist-info/licenses/LICENSE
cnquant-1.1.0.dist-info/RECORD
