Metadata-Version: 2.4
Name: cnquant
Version: 1.1.0
Summary: A股量化交易工具
Project-URL: homepage, https://github.com/axiaoqi/cnquant
Project-URL: documentation, https://github.com/axiaoqi/cnquant/blob/main/README.md
Project-URL: Bug Tracker, https://github.com/axiaoqi/cnquant/issues
Author-email: NiuGe <1091874347@qq.com>
License: MIT License
License-File: LICENSE
Classifier: License :: OSI Approved :: MIT License
Classifier: Operating System :: OS Independent
Classifier: Programming Language :: Python :: 3
Requires-Python: >=3.7
Requires-Dist: jionlp
Requires-Dist: lxml
Requires-Dist: numpy==1.26.4
Requires-Dist: openpyxl
Requires-Dist: pandas==1.5.3
Requires-Dist: pymysql
Requires-Dist: requests
Requires-Dist: retry
Requires-Dist: tqdm
